NEMO_user_details/__init__.py
NEMO_user_details/admin.py
NEMO_user_details/api.py
NEMO_user_details/apps.py
NEMO_user_details/customizations.py
NEMO_user_details/forms.py
NEMO_user_details/models.py
NEMO_user_details/urls.py
NEMO_user_details/migrations/0001_initial.py
NEMO_user_details/migrations/0002_version_1_1_0.py
NEMO_user_details/migrations/0003_version_1_3_0.py
NEMO_user_details/migrations/0004_userdetails_employee_id.py
NEMO_user_details/migrations/0005_alter_userdetails_employee_id.py
NEMO_user_details/migrations/0006_userdetails_orcid.py
NEMO_user_details/migrations/0007_userdetails_education_level.py
NEMO_user_details/migrations/0008_userdetails_google_scholar_id_and_more.py
NEMO_user_details/migrations/__init__.py
NEMO_user_details/templates/NEMO_user_details/email_broadcast.html
NEMO_user_details/templates/NEMO_user_details/user_details.html
NEMO_user_details/templates/customizations/customizations_user_details.html
NEMO_user_details/templatetags/__init__.py
NEMO_user_details/templatetags/user_details_tags.py
NEMO_user_details/views/__init__.py
NEMO_user_details/views/email.py
NEMO_user_details/views/users.py
nemo_user_details-1.11.2.dist-info/licenses/LICENSE
nemo_user_details-1.11.2.dist-info/METADATA
nemo_user_details-1.11.2.dist-info/WHEEL
nemo_user_details-1.11.2.dist-info/top_level.txt
nemo_user_details-1.11.2.dist-info/RECORD
